autodoc_typehints/__init__.py
autodoc_typehints/py.typed
autodoc_typehints-1.0.0.dist-info/LICENSE
autodoc_typehints-1.0.0.dist-info/METADATA
autodoc_typehints-1.0.0.dist-info/WHEEL
autodoc_typehints-1.0.0.dist-info/top_level.txt
autodoc_typehints-1.0.0.dist-info/RECORD
