Metadata-Version: 2.2
Name: autodoc-typehints
Version: 1.0.0
Summary: Autodoc extension to document attributes and signatures based on Python type hints.
Author: Hashberg
Project-URL: Repository, https://github.com/hashberg-io/autodoc-typehints
Project-URL: Issues, https://github.com/hashberg-io/autodoc-typehints/issues
Classifier: Programming Language :: Python :: 3
Classifier: Operating System :: OS Independent
Classifier: Development Status :: 4 - Beta
Classifier: Programming Language :: Python :: 3.13
Classifier: Programming Language :: Python :: 3.12
Classifier: Programming Language :: Python :: 3.11
Classifier: Programming Language :: Python :: 3.10
Classifier: Programming Language :: Python :: 3.9
Classifier: Natural Language :: English
Classifier: Typing :: Typed
Requires-Python: >=3.9
License-File: LICENSE
Requires-Dist: sphinx>=6.1
